edutap/wallet_google/__init__.py
edutap/wallet_google/api.py
edutap/wallet_google/plugins.py
edutap/wallet_google/protocols.py
edutap/wallet_google/py.typed
edutap/wallet_google/registry.py
edutap/wallet_google/session.py
edutap/wallet_google/settings.py
edutap/wallet_google/utils.py
edutap/wallet_google/handlers/fastapi.py
edutap/wallet_google/handlers/validate.py
edutap/wallet_google/models/__init__.py
edutap/wallet_google/models/bases.py
edutap/wallet_google/models/deprecated.py
edutap/wallet_google/models/handlers.py
edutap/wallet_google/models/misc.py
edutap/wallet_google/models/datatypes/barcode.py
edutap/wallet_google/models/datatypes/class_template_info.py
edutap/wallet_google/models/datatypes/data.py
edutap/wallet_google/models/datatypes/datetime.py
edutap/wallet_google/models/datatypes/enums.py
edutap/wallet_google/models/datatypes/event.py
edutap/wallet_google/models/datatypes/flight.py
edutap/wallet_google/models/datatypes/general.py
edutap/wallet_google/models/datatypes/jwt.py
edutap/wallet_google/models/datatypes/localized_string.py
edutap/wallet_google/models/datatypes/location.py
edutap/wallet_google/models/datatypes/loyalty.py
edutap/wallet_google/models/datatypes/message.py
edutap/wallet_google/models/datatypes/moduledata.py
edutap/wallet_google/models/datatypes/money.py
edutap/wallet_google/models/datatypes/notification.py
edutap/wallet_google/models/datatypes/retail.py
edutap/wallet_google/models/datatypes/review.py
edutap/wallet_google/models/datatypes/smarttap.py
edutap/wallet_google/models/datatypes/transit.py
edutap/wallet_google/models/passes/__init__.py
edutap/wallet_google/models/passes/bases.py
edutap/wallet_google/models/passes/generic.py
edutap/wallet_google/models/passes/retail.py
edutap/wallet_google/models/passes/tickets_and_transit.py
edutap_wallet_google-2.0.0b7.dist-info/METADATA
edutap_wallet_google-2.0.0b7.dist-info/WHEEL
edutap_wallet_google-2.0.0b7.dist-info/entry_points.txt
edutap_wallet_google-2.0.0b7.dist-info/licenses/LICENSE
edutap_wallet_google-2.0.0b7.dist-info/RECORD
