Metadata-Version: 2.4
Name: edutap.wallet-google
Version: 2.0.0b7
Summary: Library for Google Wallet Communication
Project-URL: Source, https://github.com/edutap-eu/edutap.wallet_google
Project-URL: Issues, https://github.com/edutap-eu/edutap.wallet_google/issues
Project-URL: Documentation, https://docs.edutap.eu/packages/edutap_wallet_google/index.html
Author-email: Alexander Loechel <Alexander.Loechel@lmu.de>, Philipp Auersperg-Castell <phil@bluedynamics.com>, Jens Klein <jk@kleinundpartner.at>, Robert Niederreiter <office@squarewave.at>
License: EUPL 1.2
License-File: LICENSE
Keywords: api,digital identity,fastapi,google,pass,wallet
Classifier: Development Status :: 4 - Beta
Classifier: Intended Audience :: Developers
Classifier: License :: OSI Approved :: European Union Public Licence 1.2 (EUPL 1.2)
Classifier: Operating System :: OS Independent
Classifier: Programming Language :: Python :: 3.10
Classifier: Programming Language :: Python :: 3.11
Classifier: Programming Language :: Python :: 3.12
Classifier: Programming Language :: Python :: 3.13
Classifier: Topic :: Software Development :: Libraries
Requires-Python: >=3.10
Requires-Dist: cryptography
Requires-Dist: google-auth[requests]
Requires-Dist: pydantic-settings
Requires-Dist: pydantic[email]>=2.0
Provides-Extra: callback
Requires-Dist: fastapi; extra == 'callback'
Requires-Dist: httpx; extra == 'callback'
Provides-Extra: develop
Requires-Dist: ipython; extra == 'develop'
Requires-Dist: pdbpp; extra == 'develop'
Provides-Extra: test
Requires-Dist: fastapi; extra == 'test'
Requires-Dist: httpx; extra == 'test'
Requires-Dist: pytest; extra == 'test'
Requires-Dist: pytest-cov; extra == 'test'
Requires-Dist: pytest-explicit; extra == 'test'
Requires-Dist: requests-mock; extra == 'test'
Requires-Dist: tox; extra == 'test'
Provides-Extra: typecheck
Requires-Dist: google-auth-stubs; extra == 'typecheck'
Requires-Dist: mypy; extra == 'typecheck'
Requires-Dist: pytest-stub; extra == 'typecheck'
Requires-Dist: types-cryptography; extra == 'typecheck'
